tookiyosi/__init__.py
tookiyosi/creeper.wav
tookiyosi/errors.py
tookiyosi-0.0.2.dist-info/METADATA
tookiyosi-0.0.2.dist-info/WHEEL
tookiyosi-0.0.2.dist-info/top_level.txt
tookiyosi-0.0.2.dist-info/RECORD
