Metadata-Version: 2.1
Name: tookiyosi
Version: 0.0.2
Summary: A very epic package full of epicness
Home-page: https://www.youtube.com/watch?v=dQw4w9WgXcQ
Author: TookiYosi
Author-email: tookiyosi@mailinator.com
License: UNKNOWN
Platform: UNKNOWN
Classifier: Programming Language :: Python :: 3
Classifier: Operating System :: OS Independent
Requires-Python: >=3.6
